svgling/__init__.py
svgling/__main__.py
svgling/core.py
svgling/figure.py
svgling/html.py
svgling/semantics.py
svgling/utils.py
svgling-0.5.0.dist-info/LICENSE
svgling-0.5.0.dist-info/METADATA
svgling-0.5.0.dist-info/WHEEL
svgling-0.5.0.dist-info/top_level.txt
svgling-0.5.0.dist-info/RECORD
