Metadata-Version: 2.1
Name: svgling
Version: 0.5.0
Summary: Linguistic tree diagrams in python + svg
Home-page: https://rawlins.github.io/svgling/
Author: Kyle Rawlins
Author-email: kgr@jhu.edu
License: MIT
Project-URL: Repository, https://github.com/rawlins/svgling
Classifier: Development Status :: 4 - Beta
Classifier: License :: OSI Approved :: MIT License
Classifier: Intended Audience :: Science/Research
Classifier: Topic :: Multimedia :: Graphics
Classifier: Topic :: Scientific/Engineering
Classifier: Topic :: Scientific/Engineering :: Visualization
Classifier: Topic :: Text Processing :: Linguistic
Classifier: Topic :: Text Processing :: Markup
Classifier: Topic :: Utilities
Classifier: Operating System :: OS Independent
Classifier: Programming Language :: Python
Classifier: Framework :: Jupyter
Classifier: Framework :: Jupyter :: JupyterLab
Classifier: Environment :: Web Environment
Requires-Python: >=3
License-File: LICENSE
Requires-Dist: svgwrite
Provides-Extra: conversion
Requires-Dist: cairosvg>=2.7.0; extra == "conversion"
Provides-Extra: conversion
Requires-Dist: cairosvg>=2.7.0; extra == "conversion"
Provides-Extra: all
Requires-Dist: cairosvg>=2.7.0; extra == "all"
